LICENSE
doctor_testerson/__init__.py
doctor_testerson/__main__.py
doctor_testerson/output.py
doctor_testerson/parser.py
doctor_testerson/project.py
doctor_testerson/testing.py
doctor_testerson-0.1.0.dist-info/LICENSE
doctor_testerson-0.1.0.dist-info/METADATA
doctor_testerson-0.1.0.dist-info/WHEEL
doctor_testerson-0.1.0.dist-info/entry_points.txt
doctor_testerson-0.1.0.dist-info/RECORD
