Metadata-Version: 2.1
Name: doctor-testerson
Version: 0.1.0
Summary: Provides a stupid little `dr.t` command to run Python doctests.
License: BSD-3-Clause
Author: nrser
Author-email: neil@neilsouza.com
Requires-Python: >=3.10,<4.0
Classifier: License :: OSI Approved :: BSD License
Classifier: Programming Language :: Python :: 3
Classifier: Programming Language :: Python :: 3.10
Classifier: Programming Language :: Python :: 3.11
Classifier: Programming Language :: Python :: 3
Requires-Dist: Pint (>=0.19.2,<0.20.0)
Requires-Dist: rich (>=9)
Requires-Dist: tomli (>=2.0.1,<3.0.0)
Project-URL: Homepage, https://github.com/nrser/doctor-testerson
